py_pg_notify/__init__.py
py_pg_notify/listener.py
py_pg_notify/notifier.py
py_pg_notify/pgmanager.py
py_pg_notify/utils.py
py_pg_notify-1.0.2.dist-info/LICENSE
py_pg_notify-1.0.2.dist-info/METADATA
py_pg_notify-1.0.2.dist-info/WHEEL
py_pg_notify-1.0.2.dist-info/top_level.txt
py_pg_notify-1.0.2.dist-info/RECORD
