Metadata-Version: 2.2
Name: py-pg-notify
Version: 1.0.2
Summary: Simplifies listening to and sending notifications using PostgreSQL
Author-email: D S Sanjaya <dssanjay55555@gmail.com>
License: MIT License
Project-URL: Homepage, https://github.com/DSSanjaya5/py-pg-notify
Keywords: postgresql,listen,notify,python,database,notification,postgres
Classifier: Programming Language :: Python :: 3
Classifier: License :: OSI Approved :: MIT License
Classifier: Operating System :: OS Independent
Requires-Python: >=3.10
License-File: LICENSE
Requires-Dist: asyncpg==0.30.0
Provides-Extra: dev
Requires-Dist: pytest==8.3.3; extra == "dev"
